testpackageal
