Metadata-Version: 1.1
Name: testpackageal
Version: 0.7
Summary: This is my first package.
Home-page: https://github.com/angellagunas/testpackageal
Author: Angel Lagunas
Author-email: angel.david.lagunas@gmail.com
License: UNKNOWN
Download-URL: https://github.com/angellagunas/testpackageal/tarball/0.7
Keywords: testing,logging,example
Platform: UNKNOWN
